aiml7lab.py
aiml7lab-0.0.1.dist-info/LICENSE
aiml7lab-0.0.1.dist-info/METADATA
aiml7lab-0.0.1.dist-info/WHEEL
aiml7lab-0.0.1.dist-info/top_level.txt
aiml7lab-0.0.1.dist-info/RECORD
