Metadata-Version: 2.1
Name: aiml7lab
Version: 0.0.1
Summary: aiml7lab
Author: aiml department
Author-email: aiml@gmail.com
License: MIT
Keywords: aiml7lab
Classifier: Programming Language :: Python :: 3
Classifier: License :: OSI Approved :: MIT License
Classifier: Operating System :: OS Independent
Requires-Python: >=3.7
License-File: LICENSE
